<?xml version="1.0" encoding="UTF-8"?>
<!DOCTYPE hibernate-mapping PUBLIC "-//Hibernate/Hibernate Mapping DTD 3.0//EN"
        "http://hibernate.sourceforge.net/hibernate-mapping-3.0.dtd">
<hibernate-mapping>
    <class name="com.iif.stock.entity.Stock" table="TStock">

        <id name="id" column="fid">
            <generator class="uuid"/>
        </id>

        <many-to-one name="financesId" update="false" column="ffinancesId"
                     class="com.iif.finances.entity.Finances" cascade="none" not-found="ignore">
                     
        </many-to-one>

        <property name="flag" type="integer">
            <column name="fflag" length="10"/>
        </property>

        <property name="fetchMan" type="string">
            <column name="ffetchMan" length="100"/>
        </property>

        <property name="operator" type="string">
            <column name="foperator" length="100"/>
        </property>
        
        <property name="department" type="integer">
            <column name="fdepartment" length="10"/>
        </property>

        <property name="reason" type="integer">
            <column name="freason" length="10"/>
        </property>

        <property name="isDel" type="integer">
            <column name="fisdel" length="1"/>
        </property>

        <property name="creator" type="string">
            <column name="fcreator" length="50"/>
        </property>

        <property name="createTime" type="timestamp">
            <column name="fcreatetime" length="14"/>
        </property>

        <property name="updater" type="string">
            <column name="fupdater" length="20"/>
        </property>

        <property name="updateTime" type="timestamp">
            <column name="fupdatetime" length="14"/>
        </property>
    </class>
</hibernate-mapping>